{
  "users": [
    {
      "id": "1",
      "username": "carmine",
      "password": "123"
    },
    {
      "id": "2",
      "username": "giovanni",
      "password": "234"
    }
  ],
  "books": [
    {
      "id": "87af",
      "codISBN": 9711106149565,
      "title": "Harry Potter and the Philosopher's Stone",
      "author": "J.K. Rowling",
      "dateOfPublication": "1997-06-26",
      "genre": "Fantasy"
    },
    {
      "id": "c9e2",
      "codISBN": 9780061120084,
      "title": "To Kill a Mockingbird",
      "author": "Harper Lee",
      "dateOfPublication": "1960-07-11",
      "genre": "Fantasy"
    },
    {
      "id": "3f6d",
      "codISBN": 9780743273565,
      "title": "The Great Gatsby",
      "author": "F. Scott Fitzgerald",
      "dateOfPublication": "1925-04-10",
      "genre": "Classic"
    },
    {
      "id": "a821",
      "codISBN": 9780140283334,
      "title": "1984",
      "author": "George Orwell",
      "dateOfPublication": "1949-06-08",
      "genre": "Dystopian"
    },
    {
      "id": "e4b9",
      "codISBN": 9780062315007,
      "title": "The Fault in Our Stars",
      "author": "John Green",
      "dateOfPublication": "2012-01-10",
      "genre": "Mystery"
    },
    {
      "id": "1d7f",
      "codISBN": 9788804486629,
      "title": "I promessi sposi",
      "author": "Alessandro Manzoni",
      "dateOfPublication": "1827-07-15",
      "genre": "Romance"
    },
    {
      "id": "5a2c",
      "codISBN": 9788806149565,
      "title": "Gomorra",
      "author": "Roberto Saviano",
      "dateOfPublication": "2006-11-01",
      "genre": "Romance"
    },
    {
      "id": "f8e3",
      "codISBN": 9788804666784,
      "title": "La solitudine dei numeri primi",
      "author": "Paolo Giordano",
      "dateOfPublication": "2008-09-04",
      "genre": "Romanzo"
    },
    {
      "id": "b456",
      "codISBN": 9084532153259,
      "title": "Diego Armando Maradona",
      "author": "Giuseppe Pastore",
      "dateOfPublication": "2020-11-30",
      "genre": "Bibliography"
    },
    {
      "id": "21db",
      "codISBN": 9788817018142,
      "title": "Il Codice da Vinci",
      "author": "Dan Brown",
      "dateOfPublication": "2003-03-18",
      "genre": "Mystery"
    },
    {
      "id": "26af",
      "codISBN": 9783834018142,
      "title": "Prova",
      "author": "Autore",
      "dateOfPublication": "2007-02-21",
      "genre": "Mystery"
    }
  ]
}